[
    {
        "name": "Nombank",
        "code": "090645",
        "nipCode": null,
        "logo": "https://firebasestorage.googleapis.com/v0/b/business-banking-93cc1.appspot.com/o/bankLogos%2FAmucha.png?alt=media&token=f10b52d9-0bda-4e85-b2bd-5dfa370a6feb"
    },
    {
        "name": " First Marina Trust Finance ",
        "code": "050022",
        "nipCode": null,
        "logo": ""
    },
    {
        "name": "5TT MFB ",
        "code": "090832",
        "nipCode": null,
        "logo": ""
    },
    {
        "name": "9 Payment Service Bank",
        "code": "120001",
        "nipCode": null,
        "logo": "https://firebasestorage.googleapis.com/v0/b/business-banking-93cc1.appspot.com/o/bankLogos%2FEmpty%20Bank%20Logo.png?alt=media&token=c800752e-e3f0-41cf-a4bc-de2d4017ca16"
    },
    {
        "name": "9Japay",
        "code": "090629",
        "nipCode": null,
        "logo": ""
    },
    {
        "name": "AB Microfinance Bank",
        "code": "090270",
        "nipCode": null,
        "logo": "https://firebasestorage.googleapis.com/v0/b/business-banking-93cc1.appspot.com/o/bankLogos%2FAB%20Microfinance%20Bank.png?alt=media&token=690d9845-a8fb-4b86-8d87-53a99896a7e4"
    },
    {
        "name": "AFEMAI MFB",
        "code": "090518",
        "nipCode": null,
        "logo": ""
    },
    {
        "name": "AG Mortgage Bank",
        "code": "418",
        "nipCode": null,
        "logo": ""
    },
    {
        "name": "AMAANAH FINANCE",
        "code": "050045",
        "nipCode": null,
        "logo": ""
    },
    {
        "name": "AMJU Microfinance Bank",
        "code": "090180",
        "nipCode": null,
        "logo": "https://firebasestorage.googleapis.com/v0/b/business-banking-93cc1.appspot.com/o/bankLogos%2FEmpty%20Bank%20Logo.png?alt=media&token=c800752e-e3f0-41cf-a4bc-de2d4017ca16"
    },
    {
        "name": "ARM MFB ",
        "code": "090816",
        "nipCode": null,
        "logo": ""
    },
    {
        "name": "ASO Savings & Loans",
        "code": "090001",
        "nipCode": null,
        "logo": ""
    },
    {
        "name": "ASPIRE MORTGAGE BANK",
        "code": "070033",
        "nipCode": null,
        "logo": ""
    },
    {
        "name": "AVVIC MFB",
        "code": "090853",
        "nipCode": null,
        "logo": ""
    },
    {
        "name": "Abbey Mortgage Bank",
        "code": "070010",
        "nipCode": null,
        "logo": ""
    },
    {
        "name": "Abucoop MFB",
        "code": "820",
        "nipCode": null,
        "logo": ""
    },
    {
        "name": "Access Bank",
        "code": "044",
        "nipCode": null,
        "logo": "https://firebasestorage.googleapis.com/v0/b/business-banking-93cc1.appspot.com/o/bankLogos%2FAccess%20Bank.png?alt=media&token=125c136c-5303-497e-85de-a184c48d50dd"
    },
    {
        "name": "Access Yellow",
        "code": "100052",
        "nipCode": null,
        "logo": "https://firebasestorage.googleapis.com/v0/b/business-banking-93cc1.appspot.com/o/bankLogos%2FEmpty%20Bank%20Logo.png?alt=media&token=c800752e-e3f0-41cf-a4bc-de2d4017ca16"
    },
    {
        "name": "Accion Microfinance Bank",
        "code": "090134",
        "nipCode": null,
        "logo": "https://firebasestorage.googleapis.com/v0/b/business-banking-93cc1.appspot.com/o/bankLogos%2FEmpty%20Bank%20Logo.png?alt=media&token=c800752e-e3f0-41cf-a4bc-de2d4017ca16"
    },
    {
        "name": "Adamawa Mortgage Bank ",
        "code": "070030",
        "nipCode": null,
        "logo": ""
    },
    {
        "name": "Addosser Microfinance Bank",
        "code": "090160",
        "nipCode": null,
        "logo": "https://firebasestorage.googleapis.com/v0/b/business-banking-93cc1.appspot.com/o/bankLogos%2FAddosser%20Microfinance%20Bank.png?alt=media&token=8e2b3952-18e5-4ae3-ac3b-761a7b8930e6"
    },
    {
        "name": "Aella MFB",
        "code": "090614",
        "nipCode": null,
        "logo": ""
    },
    {
        "name": "Airtel Smartcash PSB",
        "code": "120004",
        "nipCode": null,
        "logo": "https://firebasestorage.googleapis.com/v0/b/business-banking-93cc1.appspot.com/o/bankLogos%2F120004.png?alt=media&token=52a6e373-e017-4088-afbb-a0f075d2d3b7"
    },
    {
        "name": "Alternative Bank",
        "code": "100029",
        "nipCode": null,
        "logo": ""
    },
    {
        "name": "Ampersand Microfinance Bank",
        "code": "090529",
        "nipCode": null,
        "logo": "https://firebasestorage.googleapis.com/v0/b/business-banking-93cc1.appspot.com/o/bankLogos%2FEmpty%20Bank%20Logo.png?alt=media&token=c800752e-e3f0-41cf-a4bc-de2d4017ca16"
    },
    {
        "name": "Asset Matrix Microfinance Bank",
        "code": "090287",
        "nipCode": null,
        "logo": ""
    },
    {
        "name": "Auchi Microfinance Bank",
        "code": "090264",
        "nipCode": null,
        "logo": "https://firebasestorage.googleapis.com/v0/b/business-banking-93cc1.appspot.com/o/bankLogos%2FEmpty%20Bank%20Logo.png?alt=media&token=c800752e-e3f0-41cf-a4bc-de2d4017ca16"
    },
    {
        "name": "Auchi Poly MFB",
        "code": "090817",
        "nipCode": null,
        "logo": ""
    },
    {
        "name": "Avuenegbe MFB",
        "code": "090478",
        "nipCode": null,
        "logo": ""
    },
    {
        "name": "BAIGE MFB",
        "code": "090862",
        "nipCode": null,
        "logo": ""
    },
    {
        "name": "BANK78 MFB",
        "code": "090866",
        "nipCode": null,
        "logo": ""
    },
    {
        "name": "BLOC MFB",
        "code": "090977",
        "nipCode": null,
        "logo": ""
    },
    {
        "name": "BLOOMS MFB",
        "code": "090743",
        "nipCode": null,
        "logo": ""
    },
    {
        "name": "BORGU MFB",
        "code": "090395",
        "nipCode": null,
        "logo": ""
    },
    {
        "name": "Bank 78",
        "code": "110072",
        "nipCode": null,
        "logo": ""
    },
    {
        "name": "Bank of Agriculture",
        "code": "090367",
        "nipCode": null,
        "logo": ""
    },
    {
        "name": "Baobab Microfinance Bank",
        "code": "090136",
        "nipCode": null,
        "logo": ""
    },
    {
        "name": "Bestar MFB",
        "code": "090615",
        "nipCode": null,
        "logo": ""
    },
    {
        "name": "Betastack Technologies",
        "code": "110074",
        "nipCode": null,
        "logo": ""
    },
    {
        "name": "Boost MFB",
        "code": "090819",
        "nipCode": null,
        "logo": ""
    },
    {
        "name": "Bowen Microfinance Bank",
        "code": "50931",
        "nipCode": null,
        "logo": ""
    },
    {
        "name": "Bowman MFB",
        "code": "090804",
        "nipCode": null,
        "logo": ""
    },
    {
        "name": "Branch International Financial Services",
        "code": "050006",
        "nipCode": null,
        "logo": "https://firebasestorage.googleapis.com/v0/b/business-banking-93cc1.appspot.com/o/bankLogos%2Fbranch.png?alt=media&token=f4a6d4ed-73da-4cbd-bac3-20c74666ee76"
    },
    {
        "name": "Bud Infrastructure",
        "code": "983",
        "nipCode": null,
        "logo": ""
    },
    {
        "name": "Build MicroFinance Bank",
        "code": "090613",
        "nipCode": null,
        "logo": ""
    },
    {
        "name": "CASHA MFB",
        "code": "090848",
        "nipCode": null,
        "logo": ""
    },
    {
        "name": "CEDRUS MFB",
        "code": "090851",
        "nipCode": null,
        "logo": ""
    },
    {
        "name": "CEVIANT FINANCE LIMIED ",
        "code": "050043",
        "nipCode": null,
        "logo": ""
    },
    {
        "name": "Capricon Digital",
        "code": "956",
        "nipCode": null,
        "logo": ""
    },
    {
        "name": "Carbon",
        "code": "100026",
        "nipCode": null,
        "logo": "https://firebasestorage.googleapis.com/v0/b/business-banking-93cc1.appspot.com/o/bankLogos%2Fcarbon.png?alt=media&token=8d56ae93-805d-4a65-bfc5-f8a9a3c4f616"
    },
    {
        "name": "Cash Connect MFB",
        "code": "748",
        "nipCode": null,
        "logo": ""
    },
    {
        "name": "CashConnect Microfinance Bank",
        "code": "090360",
        "nipCode": null,
        "logo": ""
    },
    {
        "name": "Charis MFB",
        "code": "090815",
        "nipCode": null,
        "logo": ""
    },
    {
        "name": "Chukwunenye Microfinance Bank",
        "code": "090490",
        "nipCode": null,
        "logo": ""
    },
    {
        "name": "Citibank Nigeria Limited",
        "code": "023",
        "nipCode": null,
        "logo": "https://firebasestorage.googleapis.com/v0/b/business-banking-93cc1.appspot.com/o/bankLogos%2FCitibank%20Nigeria%20Limited.png?alt=media&token=07bab977-95d9-4113-81f5-c9c23761a017"
    },
    {
        "name": "Contec Global Infotech Limited",
        "code": "100032",
        "nipCode": null,
        "logo": "https://firebasestorage.googleapis.com/v0/b/business-banking-93cc1.appspot.com/o/bankLogos%2FEmpty%20Bank%20Logo.png?alt=media&token=c800752e-e3f0-41cf-a4bc-de2d4017ca16"
    },
    {
        "name": "Cool Microfinance Bank Limited",
        "code": "090842",
        "nipCode": null,
        "logo": ""
    },
    {
        "name": "Core Step MFB",
        "code": "766",
        "nipCode": null,
        "logo": ""
    },
    {
        "name": "Creditville MFB",
        "code": "090611",
        "nipCode": null,
        "logo": ""
    },
    {
        "name": "Crust MFB",
        "code": "090560",
        "nipCode": null,
        "logo": ""
    },
    {
        "name": "DABTIKIR MFB",
        "code": "090802",
        "nipCode": null,
        "logo": ""
    },
    {
        "name": "DEW MFB",
        "code": "090978",
        "nipCode": null,
        "logo": ""
    },
    {
        "name": "DSC Microfinance Bank",
        "code": "090821",
        "nipCode": null,
        "logo": ""
    },
    {
        "name": "Davodani Microfinance Bank",
        "code": "090391",
        "nipCode": null,
        "logo": ""
    },
    {
        "name": "Diamond Bank",
        "code": "063",
        "nipCode": null,
        "logo": "https://firebasestorage.googleapis.com/v0/b/business-banking-93cc1.appspot.com/o/bankLogos%2FAccess%20Bank.png?alt=media&token=125c136c-5303-497e-85de-a184c48d50dd"
    },
    {
        "name": "Dillon MFB ",
        "code": "090828",
        "nipCode": null,
        "logo": ""
    },
    {
        "name": "Doje Microfinance Bank Limited",
        "code": "090404",
        "nipCode": null,
        "logo": ""
    },
    {
        "name": "Dot MFB",
        "code": "090470",
        "nipCode": null,
        "logo": ""
    },
    {
        "name": "E-Settlement Ltd.",
        "code": "999999",
        "nipCode": null,
        "logo": ""
    },
    {
        "name": "EQUATOR MFB",
        "code": "090872",
        "nipCode": null,
        "logo": ""
    },
    {
        "name": "Eastman MFB ",
        "code": "090707",
        "nipCode": null,
        "logo": ""
    },
    {
        "name": "Ecobank Nigeria",
        "code": "050",
        "nipCode": null,
        "logo": "https://firebasestorage.googleapis.com/v0/b/business-banking-93cc1.appspot.com/o/bankLogos%2FEcobank%20Nigeria.png?alt=media&token=b48216b7-014b-466e-ad09-8be2cf21ce15"
    },
    {
        "name": "Ekondo Microfinance Bank",
        "code": "090097",
        "nipCode": null,
        "logo": "https://firebasestorage.googleapis.com/v0/b/business-banking-93cc1.appspot.com/o/bankLogos%2FEmpty%20Bank%20Logo.png?alt=media&token=c800752e-e3f0-41cf-a4bc-de2d4017ca16"
    },
    {
        "name": "Enrich Microfinance Bank",
        "code": "090539",
        "nipCode": null,
        "logo": "https://firebasestorage.googleapis.com/v0/b/business-banking-93cc1.appspot.com/o/bankLogos%2FEmpty%20Bank%20Logo.png?alt=media&token=c800752e-e3f0-41cf-a4bc-de2d4017ca16"
    },
    {
        "name": "Enterprise Bank",
        "code": "000019",
        "nipCode": null,
        "logo": "https://firebasestorage.googleapis.com/v0/b/business-banking-93cc1.appspot.com/o/bankLogos%2FEnterprise%20Bank.png?alt=media&token=cf3d44bd-deb6-44a2-bfab-8dfde4914d0d"
    },
    {
        "name": "FACTORING AND SUPPLY CHAIN FINANCE LIMITED",
        "code": "050042",
        "nipCode": null,
        "logo": ""
    },
    {
        "name": "FIRST LOWLAND MFB",
        "code": "090868",
        "nipCode": null,
        "logo": ""
    },
    {
        "name": "FIT MFB",
        "code": "090856",
        "nipCode": null,
        "logo": ""
    },
    {
        "name": "FSDH Merchant Bank",
        "code": "400001",
        "nipCode": null,
        "logo": ""
    },
    {
        "name": "Fairmoney Microfinance Bank",
        "code": "090551",
        "nipCode": null,
        "logo": "https://firebasestorage.googleapis.com/v0/b/business-banking-93cc1.appspot.com/o/bankLogos%2Ffairmoney.jpg?alt=media&token=d15b6d8c-7225-47d2-969a-98d49746c5a7"
    },
    {
        "name": "Fidelity Bank",
        "code": "070",
        "nipCode": null,
        "logo": "https://firebasestorage.googleapis.com/v0/b/business-banking-93cc1.appspot.com/o/bankLogos%2FFidelity%20Bank.png?alt=media&token=5a56ed69-dde6-4793-b63c-bb2f652c31b5"
    },
    {
        "name": "Finatrust MFB",
        "code": "090111",
        "nipCode": null,
        "logo": ""
    },
    {
        "name": "First Bank of Nigeria",
        "code": "011",
        "nipCode": null,
        "logo": "https://firebasestorage.googleapis.com/v0/b/business-banking-93cc1.appspot.com/o/bankLogos%2FGroup%201.png?alt=media&token=06a3a300-dafe-49db-b3d3-049371bf1173"
    },
    {
        "name": "First City Monument Bank",
        "code": "214",
        "nipCode": null,
        "logo": "https://firebasestorage.googleapis.com/v0/b/business-banking-93cc1.appspot.com/o/bankLogos%2FGroup%203.png?alt=media&token=8d223634-c044-4af8-86d4-1ac3b27711c1"
    },
    {
        "name": "First City Monument Bank MFB",
        "code": "090409",
        "nipCode": null,
        "logo": ""
    },
    {
        "name": "First Monnie Wallet",
        "code": "309",
        "nipCode": null,
        "logo": "https://firebasestorage.googleapis.com/v0/b/business-banking-93cc1.appspot.com/o/bankLogos%2FGroup%204.png?alt=media&token=7ded7f96-ef18-4833-8a05-dd52e982376e"
    },
    {
        "name": "Flexi MFB",
        "code": "090835",
        "nipCode": null,
        "logo": ""
    },
    {
        "name": "Flutterwave",
        "code": "622",
        "nipCode": null,
        "logo": "https://firebasestorage.googleapis.com/v0/b/business-banking-93cc1.appspot.com/o/bankLogos%2Fflutterwave.png?alt=media&token=f541a28d-3c94-4f9a-9de5-e0ad3fa86479"
    },
    {
        "name": "GRANULE MFB ",
        "code": "090857",
        "nipCode": null,
        "logo": ""
    },
    {
        "name": "GTBank",
        "code": "058",
        "nipCode": null,
        "logo": "https://firebasestorage.googleapis.com/v0/b/business-banking-93cc1.appspot.com/o/bankLogos%2FGroup%209.png?alt=media&token=98bde9e8-1862-495d-9046-bd3d96465970"
    },
    {
        "name": "Globus Bank",
        "code": "000027",
        "nipCode": null,
        "logo": "https://firebasestorage.googleapis.com/v0/b/business-banking-93cc1.appspot.com/o/bankLogos%2FGroup%205.png?alt=media&token=934f2462-eef3-4101-b1f9-49b663a781e3"
    },
    {
        "name": "Goldman MFB",
        "code": "090574",
        "nipCode": null,
        "logo": ""
    },
    {
        "name": "Good News Microfinance Bank",
        "code": "090495",
        "nipCode": null,
        "logo": "https://firebasestorage.googleapis.com/v0/b/business-banking-93cc1.appspot.com/o/bankLogos%2FEmpty%20Bank%20Logo.png?alt=media&token=c800752e-e3f0-41cf-a4bc-de2d4017ca16"
    },
    {
        "name": "Greenacres MFB",
        "code": "090599",
        "nipCode": null,
        "logo": ""
    },
    {
        "name": "Grooming MFB",
        "code": "090195",
        "nipCode": null,
        "logo": ""
    },
    {
        "name": "HAMADA MFB",
        "code": "090980",
        "nipCode": null,
        "logo": ""
    },
    {
        "name": "HAYAT TRUST MFB",
        "code": "090777",
        "nipCode": null,
        "logo": ""
    },
    {
        "name": "Habari Pay",
        "code": "110059",
        "nipCode": null,
        "logo": ""
    },
    {
        "name": "Hackman Microfinance Bank",
        "code": "090147",
        "nipCode": null,
        "logo": "https://firebasestorage.googleapis.com/v0/b/business-banking-93cc1.appspot.com/o/bankLogos%2FGroup%207.png?alt=media&token=9585f157-f972-4e1f-a51e-bb27906ebfec"
    },
    {
        "name": "Hala Credit Microfinance Bank",
        "code": "090291",
        "nipCode": null,
        "logo": "https://firebasestorage.googleapis.com/v0/b/business-banking-93cc1.appspot.com/o/bankLogos%2FEmpty%20Bank%20Logo.png?alt=media&token=c800752e-e3f0-41cf-a4bc-de2d4017ca16"
    },
    {
        "name": "Heritage Bank",
        "code": "030",
        "nipCode": null,
        "logo": "https://firebasestorage.googleapis.com/v0/b/business-banking-93cc1.appspot.com/o/bankLogos%2FGroup%208.png?alt=media&token=9c54e6a3-4808-4693-ad78-abfa7ff54dfc"
    },
    {
        "name": "Hope Payment Service Bank",
        "code": "120002",
        "nipCode": null,
        "logo": "https://firebasestorage.googleapis.com/v0/b/business-banking-93cc1.appspot.com/o/bankLogos%2FEmpty%20Bank%20Logo.png?alt=media&token=c800752e-e3f0-41cf-a4bc-de2d4017ca16"
    },
    {
        "name": "ILUTITUN-OSORO MFB",
        "code": "090834",
        "nipCode": null,
        "logo": ""
    },
    {
        "name": "INEBA GOGO MFB",
        "code": "090838",
        "nipCode": null,
        "logo": ""
    },
    {
        "name": "ISI-UZO MFB",
        "code": "090849",
        "nipCode": null,
        "logo": ""
    },
    {
        "name": "Ibile Microfinance Bank",
        "code": "090118",
        "nipCode": null,
        "logo": "https://firebasestorage.googleapis.com/v0/b/business-banking-93cc1.appspot.com/o/bankLogos%2FEmpty%20Bank%20Logo.png?alt=media&token=c800752e-e3f0-41cf-a4bc-de2d4017ca16"
    },
    {
        "name": "Ikoyi Osun MFB",
        "code": "090536",
        "nipCode": null,
        "logo": ""
    },
    {
        "name": "Jaiz Bank",
        "code": "301",
        "nipCode": null,
        "logo": "https://firebasestorage.googleapis.com/v0/b/business-banking-93cc1.appspot.com/o/bankLogos%2FGroup%2010.png?alt=media&token=7c29c936-8e11-44ee-94c6-8e40175d18a3"
    },
    {
        "name": "Jubilee-Life Mortgage  Bank",
        "code": "090003",
        "nipCode": null,
        "logo": ""
    },
    {
        "name": "KKU MFB",
        "code": "090606",
        "nipCode": null,
        "logo": ""
    },
    {
        "name": "KOBOWEB MFB",
        "code": "090865",
        "nipCode": null,
        "logo": ""
    },
    {
        "name": "KOINS MFB",
        "code": "090839",
        "nipCode": null,
        "logo": ""
    },
    {
        "name": "Kenechukwu Microfinance Bank",
        "code": "090602",
        "nipCode": null,
        "logo": "https://firebasestorage.googleapis.com/v0/b/business-banking-93cc1.appspot.com/o/bankLogos%2FEmpty%20Bank%20Logo.png?alt=media&token=c800752e-e3f0-41cf-a4bc-de2d4017ca16"
    },
    {
        "name": "Key Stone Bank",
        "code": "082",
        "nipCode": null,
        "logo": "https://firebasestorage.googleapis.com/v0/b/business-banking-93cc1.appspot.com/o/bankLogos%2FGroup%2011.png?alt=media&token=bd792e3b-0574-4f3a-a0dd-7601c9e657c4"
    },
    {
        "name": "Kolomoni MFB",
        "code": "899",
        "nipCode": null,
        "logo": ""
    },
    {
        "name": "Konga Pay",
        "code": "100025",
        "nipCode": null,
        "logo": ""
    },
    {
        "name": "Kredi Microfinance Bank",
        "code": "090380",
        "nipCode": null,
        "logo": "https://firebasestorage.googleapis.com/v0/b/business-banking-93cc1.appspot.com/o/bankLogos%2FEmpty%20Bank%20Logo.png?alt=media&token=c800752e-e3f0-41cf-a4bc-de2d4017ca16"
    },
    {
        "name": "Kuda Microfinance Bank",
        "code": "090267",
        "nipCode": null,
        "logo": "https://firebasestorage.googleapis.com/v0/b/business-banking-93cc1.appspot.com/o/bankLogos%2FGroup%2012.png?alt=media&token=b835b9a4-b413-4fb3-9d28-c71fe1dda86d"
    },
    {
        "name": "LIVINGTRUST MORTGAGE BANK",
        "code": "070007",
        "nipCode": null,
        "logo": ""
    },
    {
        "name": "LOMA BANK",
        "code": "090620",
        "nipCode": null,
        "logo": ""
    },
    {
        "name": "Lapo Microfinance Bank",
        "code": "090177",
        "nipCode": null,
        "logo": "https://firebasestorage.googleapis.com/v0/b/business-banking-93cc1.appspot.com/o/bankLogos%2Flapo.png?alt=media&token=b2f78827-cb39-410f-a14c-6567ebd3c1ff"
    },
    {
        "name": "LeadCity MFB",
        "code": "397",
        "nipCode": null,
        "logo": ""
    },
    {
        "name": "Letshego Microfinance Bank",
        "code": "090420",
        "nipCode": null,
        "logo": "https://firebasestorage.googleapis.com/v0/b/business-banking-93cc1.appspot.com/o/bankLogos%2FEmpty%20Bank%20Logo.png?alt=media&token=c800752e-e3f0-41cf-a4bc-de2d4017ca16"
    },
    {
        "name": "Lotus Bank",
        "code": "000029",
        "nipCode": null,
        "logo": "https://firebasestorage.googleapis.com/v0/b/business-banking-93cc1.appspot.com/o/bankLogos%2FLotus.png?alt=media&token=1fc3cb60-95ef-48a0-ba10-538d9ffd43dd"
    },
    {
        "name": "MAHFUZ MFB",
        "code": "090825",
        "nipCode": null,
        "logo": ""
    },
    {
        "name": "MAXITRUST MFB",
        "code": "090843",
        "nipCode": null,
        "logo": ""
    },
    {
        "name": "MAYDEN MFB ",
        "code": "090854",
        "nipCode": null,
        "logo": ""
    },
    {
        "name": "MEMENTO MFB",
        "code": "090867",
        "nipCode": null,
        "logo": ""
    },
    {
        "name": "MIA MFB",
        "code": "090859",
        "nipCode": null,
        "logo": ""
    },
    {
        "name": "MKUDI",
        "code": "100011",
        "nipCode": null,
        "logo": ""
    },
    {
        "name": "MOVASCO-OP MFB",
        "code": "090979",
        "nipCode": null,
        "logo": ""
    },
    {
        "name": "Mainstreet Microfinance Bank",
        "code": "090171",
        "nipCode": null,
        "logo": "https://firebasestorage.googleapis.com/v0/b/business-banking-93cc1.appspot.com/o/bankLogos%2FEmpty%20Bank%20Logo.png?alt=media&token=c800752e-e3f0-41cf-a4bc-de2d4017ca16"
    },
    {
        "name": "Malachy MFB",
        "code": "648",
        "nipCode": null,
        "logo": ""
    },
    {
        "name": "Mega MFB",
        "code": "090824",
        "nipCode": null,
        "logo": ""
    },
    {
        "name": "Mkobo Microfinance Bank",
        "code": "090455",
        "nipCode": null,
        "logo": "https://firebasestorage.googleapis.com/v0/b/business-banking-93cc1.appspot.com/o/bankLogos%2FEmpty%20Bank%20Logo.png?alt=media&token=c800752e-e3f0-41cf-a4bc-de2d4017ca16"
    },
    {
        "name": "Momo Payment Service Bank",
        "code": "120003",
        "nipCode": null,
        "logo": "https://firebasestorage.googleapis.com/v0/b/business-banking-93cc1.appspot.com/o/bankLogos%2FMoMo-PSB.webp?alt=media&token=409142b5-69f0-4dc0-8993-c9e1d29b5baa"
    },
    {
        "name": "Moneytronics MFB",
        "code": "090692",
        "nipCode": null,
        "logo": ""
    },
    {
        "name": "Moniepoint Microfinance Bank",
        "code": "090405",
        "nipCode": null,
        "logo": "https://firebasestorage.googleapis.com/v0/b/business-banking-93cc1.appspot.com/o/bankLogos%2FMoniepoint.png?alt=media&token=0116b22d-60c8-4ec8-9d29-6f3d1eb73afc"
    },
    {
        "name": "Moremonee Microfinance Bank Limited",
        "code": "090685",
        "nipCode": null,
        "logo": ""
    },
    {
        "name": "NOVEL MFB",
        "code": "090863",
        "nipCode": null,
        "logo": ""
    },
    {
        "name": "NPF MicroFinance Bank",
        "code": "070001",
        "nipCode": null,
        "logo": ""
    },
    {
        "name": "NSUKKA MFB",
        "code": "090356",
        "nipCode": null,
        "logo": ""
    },
    {
        "name": "Netapps Technology",
        "code": "950",
        "nipCode": null,
        "logo": ""
    },
    {
        "name": "Nirsal MFB",
        "code": "090194",
        "nipCode": null,
        "logo": "https://firebasestorage.googleapis.com/v0/b/business-banking-93cc1.appspot.com/o/bankLogos%2FEmpty%20Bank%20Logo.png?alt=media&token=c800752e-e3f0-41cf-a4bc-de2d4017ca16"
    },
    {
        "name": "Noun MFB",
        "code": "090822",
        "nipCode": null,
        "logo": ""
    },
    {
        "name": "OAU Microfinance Bank",
        "code": "090345",
        "nipCode": null,
        "logo": "https://firebasestorage.googleapis.com/v0/b/business-banking-93cc1.appspot.com/o/bankLogos%2FEmpty%20Bank%20Logo.png?alt=media&token=c800752e-e3f0-41cf-a4bc-de2d4017ca16"
    },
    {
        "name": "OBA MFB",
        "code": "090981",
        "nipCode": null,
        "logo": ""
    },
    {
        "name": "OLOMU APERAN MFB",
        "code": "090852",
        "nipCode": null,
        "logo": ""
    },
    {
        "name": "Omiye MFB",
        "code": "090295",
        "nipCode": null,
        "logo": ""
    },
    {
        "name": "Optimus Bank",
        "code": "000036",
        "nipCode": null,
        "logo": "https://share.google/images/M5JteKIW7MrxJi7IH"
    },
    {
        "name": "PATHFINDER MFB",
        "code": "090680",
        "nipCode": null,
        "logo": ""
    },
    {
        "name": "PAYREP MFB",
        "code": "090823",
        "nipCode": null,
        "logo": ""
    },
    {
        "name": "PENTECOST MFB",
        "code": "090861",
        "nipCode": null,
        "logo": ""
    },
    {
        "name": "Paga",
        "code": "327",
        "nipCode": null,
        "logo": "https://firebasestorage.googleapis.com/v0/b/business-banking-93cc1.appspot.com/o/bankLogos%2FPaga.png?alt=media&token=1a806180-b3d3-46c8-9b22-b317ff20274c"
    },
    {
        "name": "Page Financials",
        "code": "070008",
        "nipCode": null,
        "logo": "https://firebasestorage.googleapis.com/v0/b/business-banking-93cc1.appspot.com/o/bankLogos%2FEmpty%20Bank%20Logo.png?alt=media&token=c800752e-e3f0-41cf-a4bc-de2d4017ca16"
    },
    {
        "name": "Palmpay",
        "code": "100033",
        "nipCode": null,
        "logo": "https://firebasestorage.googleapis.com/v0/b/business-banking-93cc1.appspot.com/o/bankLogos%2FPalmpay.png?alt=media&token=3a037b7d-84af-4147-8022-760f5fae669a"
    },
    {
        "name": "Parallex MF Bank",
        "code": "000030",
        "nipCode": null,
        "logo": "https://firebasestorage.googleapis.com/v0/b/business-banking-93cc1.appspot.com/o/bankLogos%2FGroup%2028.png?alt=media&token=52665582-6e2d-4702-955c-e18f5ea82430"
    },
    {
        "name": "Parkway-ReadyCash",
        "code": "100003",
        "nipCode": null,
        "logo": ""
    },
    {
        "name": "PayAttitude Online",
        "code": "329",
        "nipCode": null,
        "logo": "https://firebasestorage.googleapis.com/v0/b/business-banking-93cc1.appspot.com/o/bankLogos%2Fimage%2039.png?alt=media&token=71e9496e-a035-4945-8b50-14620cb802e1"
    },
    {
        "name": "Paycom (Opay)",
        "code": "305",
        "nipCode": null,
        "logo": "https://firebasestorage.googleapis.com/v0/b/business-banking-93cc1.appspot.com/o/bankLogos%2FGroup%2013.png?alt=media&token=adea70b7-71c8-4880-9380-e7d23d6d06b5"
    },
    {
        "name": "Paystack Titan",
        "code": "100039",
        "nipCode": null,
        "logo": "https://firebasestorage.googleapis.com/v0/b/business-banking-93cc1.appspot.com/o/bankLogos%2FPaystack.png?alt=media&token=1134e886-0537-4437-b838-d7fe4ca838f9"
    },
    {
        "name": "Pocket App",
        "code": "100042",
        "nipCode": null,
        "logo": ""
    },
    {
        "name": "Poder finance ",
        "code": "050021",
        "nipCode": null,
        "logo": ""
    },
    {
        "name": "Polaris Bank",
        "code": "076",
        "nipCode": null,
        "logo": "https://firebasestorage.googleapis.com/v0/b/business-banking-93cc1.appspot.com/o/bankLogos%2FGroup%2017.png?alt=media&token=64892918-dcc1-419d-aab1-581adce0c3f8"
    },
    {
        "name": "Premium Trust Bank",
        "code": "000031",
        "nipCode": null,
        "logo": "https://firebasestorage.googleapis.com/v0/b/business-banking-93cc1.appspot.com/o/bankLogos%2Fpremium.png?alt=media&token=573200b2-437f-4774-a5ff-40dcb15ca385"
    },
    {
        "name": "Pristine Divitis Microfinance Bank",
        "code": "090499",
        "nipCode": null,
        "logo": "https://firebasestorage.googleapis.com/v0/b/business-banking-93cc1.appspot.com/o/bankLogos%2FEmpty%20Bank%20Logo.png?alt=media&token=c800752e-e3f0-41cf-a4bc-de2d4017ca16"
    },
    {
        "name": "Projetcs Microfinance Bank",
        "code": "090503",
        "nipCode": null,
        "logo": "https://firebasestorage.googleapis.com/v0/b/business-banking-93cc1.appspot.com/o/bankLogos%2FEmpty%20Bank%20Logo.png?alt=media&token=c800752e-e3f0-41cf-a4bc-de2d4017ca16"
    },
    {
        "name": "Prospa Capital MFB",
        "code": "50739",
        "nipCode": null,
        "logo": ""
    },
    {
        "name": "Providus Bank",
        "code": "101",
        "nipCode": null,
        "logo": "https://firebasestorage.googleapis.com/v0/b/business-banking-93cc1.appspot.com/o/bankLogos%2Fimage%2040.png?alt=media&token=987e50e2-e36b-4ab4-963b-e1a11e937da4"
    },
    {
        "name": "RIMIN GADO MFB",
        "code": "090713",
        "nipCode": null,
        "logo": ""
    },
    {
        "name": "Randalpha Microfinance Bank",
        "code": "090496",
        "nipCode": null,
        "logo": "https://firebasestorage.googleapis.com/v0/b/business-banking-93cc1.appspot.com/o/bankLogos%2FEmpty%20Bank%20Logo.png?alt=media&token=c800752e-e3f0-41cf-a4bc-de2d4017ca16"
    },
    {
        "name": "RenMoney Microfinance Bank",
        "code": "090198",
        "nipCode": null,
        "logo": "https://firebasestorage.googleapis.com/v0/b/business-banking-93cc1.appspot.com/o/bankLogos%2FGroup%2014.png?alt=media&token=44818d67-86d2-4324-acd8-0decb5297293"
    },
    {
        "name": "Royal Exchange Microfinance Bank",
        "code": "090138",
        "nipCode": null,
        "logo": "https://firebasestorage.googleapis.com/v0/b/business-banking-93cc1.appspot.com/o/bankLogos%2FEmpty%20Bank%20Logo.png?alt=media&token=c800752e-e3f0-41cf-a4bc-de2d4017ca16"
    },
    {
        "name": "Rubies MFB",
        "code": "090175",
        "nipCode": null,
        "logo": ""
    },
    {
        "name": "SOSA MFB ",
        "code": "090836",
        "nipCode": null,
        "logo": ""
    },
    {
        "name": "SPRINGVILLE MFB",
        "code": "090786",
        "nipCode": null,
        "logo": ""
    },
    {
        "name": "SYCAMORE MFB",
        "code": "090827",
        "nipCode": null,
        "logo": ""
    },
    {
        "name": "Safe Haven MFB",
        "code": "090286",
        "nipCode": null,
        "logo": ""
    },
    {
        "name": "Sciart Finance",
        "code": "050024",
        "nipCode": null,
        "logo": ""
    },
    {
        "name": "Shalom Microfinance Bank",
        "code": "090502",
        "nipCode": null,
        "logo": "https://firebasestorage.googleapis.com/v0/b/business-banking-93cc1.appspot.com/o/bankLogos%2FEmpty%20Bank%20Logo.png?alt=media&token=c800752e-e3f0-41cf-a4bc-de2d4017ca16"
    },
    {
        "name": "Smart Cash PSB",
        "code": "942",
        "nipCode": null,
        "logo": ""
    },
    {
        "name": "Source MFB",
        "code": "090641",
        "nipCode": null,
        "logo": ""
    },
    {
        "name": "Sparkle",
        "code": "090325",
        "nipCode": null,
        "logo": "https://firebasestorage.googleapis.com/v0/b/business-banking-93cc1.appspot.com/o/bankLogos%2Fsparkle.png?alt=media&token=f8d44cae-ac07-4fbb-9b83-baa839955ed2"
    },
    {
        "name": "Spectrum MFB",
        "code": "090436",
        "nipCode": null,
        "logo": ""
    },
    {
        "name": "Stanbic IBTC Bank",
        "code": "039",
        "nipCode": null,
        "logo": "https://firebasestorage.googleapis.com/v0/b/business-banking-93cc1.appspot.com/o/bankLogos%2FGroup%2016.png?alt=media&token=cf0cc320-01e3-4290-a417-ffca9eb04873"
    },
    {
        "name": "Standard Chartered Bank Nigeria",
        "code": "068",
        "nipCode": null,
        "logo": "https://firebasestorage.googleapis.com/v0/b/business-banking-93cc1.appspot.com/o/bankLogos%2FGroup%2015.png?alt=media&token=0fee909b-ebbb-4138-93c6-3c86bf5dc7d9"
    },
    {
        "name": "Stellas MFB",
        "code": "667",
        "nipCode": null,
        "logo": ""
    },
    {
        "name": "Sterling Bank Plc",
        "code": "232",
        "nipCode": null,
        "logo": "https://firebasestorage.googleapis.com/v0/b/business-banking-93cc1.appspot.com/o/bankLogos%2FGroup%2019.png?alt=media&token=d91c3fbe-1bd9-4571-9ae5-d14d4c098678"
    },
    {
        "name": "Summit Bank",
        "code": "080003",
        "nipCode": null,
        "logo": ""
    },
    {
        "name": "SunTrust Bank Nigeria Limited",
        "code": "100",
        "nipCode": null,
        "logo": "https://firebasestorage.googleapis.com/v0/b/business-banking-93cc1.appspot.com/o/bankLogos%2FEmpty%20Bank%20Logo.png?alt=media&token=c800752e-e3f0-41cf-a4bc-de2d4017ca16"
    },
    {
        "name": "TENN MFB",
        "code": "090716",
        "nipCode": null,
        "logo": ""
    },
    {
        "name": "Taj Bank",
        "code": "000026",
        "nipCode": null,
        "logo": "https://firebasestorage.googleapis.com/v0/b/business-banking-93cc1.appspot.com/o/bankLogos%2FGroup%2021.png?alt=media&token=b4d4f7bc-d6d9-4852-adf5-d092d852ca82"
    },
    {
        "name": "Tatum Bank",
        "code": "000042",
        "nipCode": null,
        "logo": ""
    },
    {
        "name": "Tellerone MFB",
        "code": "090788",
        "nipCode": null,
        "logo": ""
    },
    {
        "name": "Titan Trust Bank",
        "code": "000025",
        "nipCode": null,
        "logo": "https://firebasestorage.googleapis.com/v0/b/business-banking-93cc1.appspot.com/o/bankLogos%2FGroup%2022.png?alt=media&token=083e9720-b011-4875-92a3-22626c31bda2"
    },
    {
        "name": "Toprate Microfinance Bank",
        "code": "090801",
        "nipCode": null,
        "logo": ""
    },
    {
        "name": "UNN Microfinance Bank",
        "code": "090251",
        "nipCode": null,
        "logo": "https://firebasestorage.googleapis.com/v0/b/business-banking-93cc1.appspot.com/o/bankLogos%2FEmpty%20Bank%20Logo.png?alt=media&token=c800752e-e3f0-41cf-a4bc-de2d4017ca16"
    },
    {
        "name": "URE MICROFINANCE BANK",
        "code": "090619",
        "nipCode": null,
        "logo": ""
    },
    {
        "name": "Uda MFB",
        "code": "672",
        "nipCode": null,
        "logo": ""
    },
    {
        "name": "Ukpor MFB",
        "code": " 090820",
        "nipCode": null,
        "logo": ""
    },
    {
        "name": "Umuoji MFB",
        "code": "090814",
        "nipCode": null,
        "logo": ""
    },
    {
        "name": "Unical MFB",
        "code": "090193",
        "nipCode": null,
        "logo": ""
    },
    {
        "name": "Unilag MFB",
        "code": "090452",
        "nipCode": null,
        "logo": ""
    },
    {
        "name": "Union Bank of Nigeria",
        "code": "032",
        "nipCode": null,
        "logo": "https://firebasestorage.googleapis.com/v0/b/business-banking-93cc1.appspot.com/o/bankLogos%2FGroup%2026.png?alt=media&token=f06c7ce9-886d-411f-abbb-50aaaa56ca0c"
    },
    {
        "name": "United Bank for Africa",
        "code": "033",
        "nipCode": null,
        "logo": "https://firebasestorage.googleapis.com/v0/b/business-banking-93cc1.appspot.com/o/bankLogos%2FGroup%2025.png?alt=media&token=a2a144de-9c8b-4811-8278-7666746486ee"
    },
    {
        "name": "Unity Bank",
        "code": "215",
        "nipCode": null,
        "logo": "https://firebasestorage.googleapis.com/v0/b/business-banking-93cc1.appspot.com/o/bankLogos%2FGroup%2024.png?alt=media&token=adc5db85-812f-47d3-9669-fd75623dfdc8"
    },
    {
        "name": "VFD Microfinance Bank Limited",
        "code": "566",
        "nipCode": null,
        "logo": "https://firebasestorage.googleapis.com/v0/b/business-banking-93cc1.appspot.com/o/bankLogos%2Fvfd.png?alt=media&token=4dc412d8-9d7c-49ba-9cc8-d106712ed121"
    },
    {
        "name": "Vale Finance",
        "code": "050020",
        "nipCode": null,
        "logo": ""
    },
    {
        "name": "Victory MFB",
        "code": "090813",
        "nipCode": null,
        "logo": ""
    },
    {
        "name": "Wema Bank",
        "code": "035",
        "nipCode": null,
        "logo": "https://firebasestorage.googleapis.com/v0/b/business-banking-93cc1.appspot.com/o/bankLogos%2FGroup%2023.png?alt=media&token=94db8c36-2b16-490d-900c-32a3787356ca"
    },
    {
        "name": "Whitecrust Finance",
        "code": "050035",
        "nipCode": null,
        "logo": ""
    },
    {
        "name": "XPress MTS",
        "code": "148",
        "nipCode": null,
        "logo": ""
    },
    {
        "name": "XPress Payments",
        "code": "738",
        "nipCode": null,
        "logo": ""
    },
    {
        "name": "XPress Wallet",
        "code": "391",
        "nipCode": null,
        "logo": ""
    },
    {
        "name": "Yello Digital Services",
        "code": "964",
        "nipCode": null,
        "logo": ""
    },
    {
        "name": "ZWallet",
        "code": "792",
        "nipCode": null,
        "logo": ""
    },
    {
        "name": "Zenith Bank",
        "code": "057",
        "nipCode": null,
        "logo": "https://firebasestorage.googleapis.com/v0/b/business-banking-93cc1.appspot.com/o/bankLogos%2FGroup%2029.png?alt=media&token=aea9f53c-c7d4-4e8d-9d6a-3bca87a54c22"
    },
    {
        "name": "Zikora Microfinance Bank",
        "code": "090504",
        "nipCode": null,
        "logo": "https://firebasestorage.googleapis.com/v0/b/business-banking-93cc1.appspot.com/o/bankLogos%2FEmpty%20Bank%20Logo.png?alt=media&token=c800752e-e3f0-41cf-a4bc-de2d4017ca16"
    },
    {
        "name": "eTranzact",
        "code": "306",
        "nipCode": null,
        "logo": "https://firebasestorage.googleapis.com/v0/b/business-banking-93cc1.appspot.com/o/bankLogos%2FeTranzact.png?alt=media&token=49d1bd4e-c490-49ab-af73-1b6c12e0d946"
    }
]